trustme_cli.py
trustme_cli-2020.2.28.dist-info/entry_points.txt
trustme_cli-2020.2.28.dist-info/LICENSE
trustme_cli-2020.2.28.dist-info/WHEEL
trustme_cli-2020.2.28.dist-info/METADATA
trustme_cli-2020.2.28.dist-info/RECORD
