Metadata-Version: 2.1
Name: trustme_cli
Version: 2020.2.28
Summary: A simple tool that generates certificates for local testing
Home-page: https://github.com/sethmlarson/trustme-cli
License: UNKNOWN
Author: Seth Michael Larson
Author-email: sethmichaellarson@gmail.com
Requires-Python: >=3.6
Classifier: License :: OSI Approved :: MIT License
Requires-Dist: trustme
